LICENSE
NOTICE
README.md
setup.cfg
setup.py
UniswapPy.egg-info/PKG-INFO
UniswapPy.egg-info/SOURCES.txt
UniswapPy.egg-info/dependency_links.txt
UniswapPy.egg-info/not-zip-safe
UniswapPy.egg-info/requires.txt
UniswapPy.egg-info/top_level.txt
python/prod/__init__.py
python/prod/analytics/risk/UniswapImpLoss.py
python/prod/analytics/risk/__init__.py
python/prod/analytics/simulate/Arbitrage.py
python/prod/analytics/simulate/CorrectReserves.py
python/prod/analytics/simulate/MarkovState.py
python/prod/analytics/simulate/QuantTerminal.py
python/prod/analytics/simulate/SimpleLPSimulation.py
python/prod/analytics/simulate/SolveDeltas.py
python/prod/analytics/simulate/TokenSupplyState.py
python/prod/analytics/simulate/__init__.py
python/prod/cpt/exchg/ChildLP.py
python/prod/cpt/exchg/ChildUniswapExchange.py
python/prod/cpt/exchg/UniswapExchange.py
python/prod/cpt/exchg/UniswapV3Exchange.py
python/prod/cpt/exchg/__init__.py
python/prod/cpt/factory/UniswapFactory.py
python/prod/cpt/factory/__init__.py
python/prod/cpt/index/RebaseIndexToken.py
python/prod/cpt/index/SettlementLPToken.py
python/prod/cpt/index/__init__.py
python/prod/cpt/quote/IndexTokenQuote.py
python/prod/cpt/quote/LPQuote.py
python/prod/cpt/quote/LPTokenQuote.py
python/prod/cpt/quote/QuoteLiquidity.py
python/prod/cpt/quote/TreeAmountQuote.py
python/prod/cpt/quote/__init__.py
python/prod/cpt/vault/IndexVault.py
python/prod/cpt/vault/Vault.py
python/prod/cpt/vault/__init__.py
python/prod/cpt/wallet/Wallets.py
python/prod/cpt/wallet/__init__.py
python/prod/erc/DOAERC20.py
python/prod/erc/ERC20.py
python/prod/erc/IndexERC20.py
python/prod/erc/LPERC20.py
python/prod/erc/__init__.py
python/prod/math/basic/IDGenerator.py
python/prod/math/basic/RoundFloat.py
python/prod/math/basic/__init__.py
python/prod/math/interest/CompoundReturn.py
python/prod/math/interest/Yield.py
python/prod/math/interest/__init__.py
python/prod/math/interest/ips/ConstantIPS.py
python/prod/math/interest/ips/IPS.py
python/prod/math/interest/ips/__init__.py
python/prod/math/interest/ips/aggregate/AggregateIPS.py
python/prod/math/interest/ips/aggregate/__init__.py
python/prod/math/model/BrownianModel.py
