Metadata-Version: 2.1
Name: UniswapPy
Version: 1.7.5
Summary: Uniswap Analytics with Python
Home-page: https://github.com/defipy-devs/uniswappy
Author: icmoore
Author-email: defipy.devs@gmail.com
License: Apache-2.0
Classifier: License :: OSI Approved :: Apache Software License
Classifier: Programming Language :: Python :: 3
Classifier: Operating System :: OS Independent
Classifier: Intended Audience :: Developers
Classifier: Topic :: Software Development :: Libraries :: Python Modules
Classifier: Topic :: Scientific/Engineering :: Information Analysis
Classifier: Topic :: Internet :: WWW/HTTP :: Dynamic Content
License-File: LICENSE
License-File: NOTICE
Requires-Dist: scipy>=1.7.3
Requires-Dist: termcolor>=2.4.0
